pymodlib/PyMod.py
pymodlib/__init__.py
pymodlib-1.0.0.dist-info/LICENSE
pymodlib-1.0.0.dist-info/METADATA
pymodlib-1.0.0.dist-info/WHEEL
pymodlib-1.0.0.dist-info/top_level.txt
pymodlib-1.0.0.dist-info/RECORD
