Metadata-Version: 2.1
Name: pymodlib
Version: 1.0.0
Summary: Modbus Server for PLC Siemens LOGO8
Home-page: https://github.com/ignaciojuica/PyMod
Author: Ignacio Juica
Author-email: electric.sspa@gmail.com
License: UNKNOWN
Platform: UNKNOWN
Classifier: Programming Language :: Python :: 3
Classifier: License :: OSI Approved :: MIT License
Classifier: Operating System :: OS Independent
Requires-Python: >=3.6
